gnssrefl/EGM96.py
gnssrefl/__init__.py
gnssrefl/cddis_highrate.py
gnssrefl/check_rinex.py
gnssrefl/check_rinex2.py
gnssrefl/computemp1mp2.py
gnssrefl/daily_avg.py
gnssrefl/daily_avg_cl.py
gnssrefl/download_ioc.py
gnssrefl/download_orbits.py
gnssrefl/download_rinex.py
gnssrefl/download_simon.py
gnssrefl/download_teqc.py
gnssrefl/download_tides.py
gnssrefl/download_unr.py
gnssrefl/filesizes.py
gnssrefl/gnssir.py
gnssrefl/gnssir_cl.py
gnssrefl/gnsssnr.cpython-39-darwin.so
gnssrefl/gnsssnrbigger.cpython-39-darwin.so
gnssrefl/gps.py
gnssrefl/gpssnr.cpython-39-darwin.so
gnssrefl/gpsweek.py
gnssrefl/installexe_cl.py
gnssrefl/invsnr_cl.py
gnssrefl/invsnr_input.py
gnssrefl/karnak_libraries.py
gnssrefl/llh2xyz.py
gnssrefl/make_json_input.py
gnssrefl/nmea2snr.py
gnssrefl/nmea2snr_cl.py
gnssrefl/phase_functions.py
gnssrefl/prn2gps.py
gnssrefl/qplt.py
gnssrefl/qplt2.py
gnssrefl/query_unr.py
gnssrefl/quickLook_cl.py
gnssrefl/quickLook_function.py
gnssrefl/quickPhase.py
gnssrefl/quickPhase_function.py
gnssrefl/read_snr_files.py
gnssrefl/refl_zones.py
gnssrefl/refl_zones_cl.py
gnssrefl/refraction.py
gnssrefl/rinex2snr.py
gnssrefl/rinex2snr_cl.py
gnssrefl/rinex3_rinex2.py
gnssrefl/rinex3_snr.py
gnssrefl/rinpy.py
gnssrefl/spline_functions.py
gnssrefl/subdaily.py
gnssrefl/subdaily_cl.py
gnssrefl/utils.py
gnssrefl/veg_multiyr.py
gnssrefl/vwc.py
gnssrefl/vwc_input.py
gnssrefl/xyz2llh.py
gnssrefl/ydoy.py
gnssrefl/ymd.py
gnssrefl-1.2.7.dist-info/LICENSE
gnssrefl-1.2.7.dist-info/METADATA
gnssrefl-1.2.7.dist-info/WHEEL
gnssrefl-1.2.7.dist-info/entry_points.txt
gnssrefl-1.2.7.dist-info/top_level.txt
gnssrefl-1.2.7.dist-info/RECORD
