Metadata-Version: 2.1
Name: gnssrefl
Version: 1.2.7
Summary: A GNSS reflectometry software package 
Home-page: https://github.com/kristinemlarson/gnssrefl/
Author: Kristine Larson
Author-email: kristinem.larson@gmail.com
License: UNKNOWN
Platform: UNKNOWN
Classifier: Programming Language :: Python :: 3.9
Classifier: License :: OSI Approved :: GNU General Public License v3 (GPLv3)
License-File: LICENSE
Requires-Dist: numpy
Requires-Dist: wget
Requires-Dist: scipy
Requires-Dist: matplotlib
Requires-Dist: requests
Requires-Dist: progress
Requires-Dist: astropy
Requires-Dist: simplekml
